azure/__init__.py
azure/cli/__init__.py
azure/cli/command_modules/__init__.py
azure/cli/command_modules/sql/__init__.py
azure/cli/command_modules/sql/_format.py
azure/cli/command_modules/sql/_help.py
azure/cli/command_modules/sql/_params.py
azure/cli/command_modules/sql/_util.py
azure/cli/command_modules/sql/_validators.py
azure/cli/command_modules/sql/commands.py
azure/cli/command_modules/sql/custom.py
azure_cli_sql-2.2.5.dist-info/METADATA
azure_cli_sql-2.2.5.dist-info/WHEEL
azure_cli_sql-2.2.5.dist-info/top_level.txt
azure_cli_sql-2.2.5.dist-info/RECORD
