Metadata-Version: 2.1
Name: azure-cli-sql
Version: 2.2.5
Summary: Microsoft Azure Command-Line Tools SQL Command Module
Home-page: https://github.com/Azure/azure-cli
Author: Microsoft Corporation
Author-email: azpycli@microsoft.com
License: MIT
Platform: UNKNOWN
Classifier: Development Status :: 4 - Beta
Classifier: Intended Audience :: Developers
Classifier: Intended Audience :: System Administrators
Classifier: Programming Language :: Python
Classifier: Programming Language :: Python :: 2
Classifier: Programming Language :: Python :: 2.7
Classifier: Programming Language :: Python :: 3
Classifier: Programming Language :: Python :: 3.4
Classifier: Programming Language :: Python :: 3.5
Classifier: Programming Language :: Python :: 3.6
Classifier: License :: OSI Approved :: MIT License
Requires-Dist: azure-cli-core
Requires-Dist: azure-mgmt-sql (==0.12.0)
Requires-Dist: azure-mgmt-storage (==3.3.0)
Requires-Dist: six
Requires-Dist: azure-cli-command-modules-nspkg (>=2.0.0)
